eaheog/__init__.py
eaheog/client.py
eaheog-0.1.4.dist-info/METADATA
eaheog-0.1.4.dist-info/WHEEL
eaheog-0.1.4.dist-info/top_level.txt
eaheog-0.1.4.dist-info/RECORD
