Metadata-Version: 2.4
Name: eaheog
Version: 0.1.4
Summary: EOG-HPO Client SDK for intelligent hyperparameter recommendations
Author: HK Pandey
Classifier: Programming Language :: Python :: 3
Classifier: Operating System :: OS Independent
Requires-Python: >=3.6
Requires-Dist: requests>=2.25.0
Provides-Extra: viz
Requires-Dist: pandas; extra == "viz"
Requires-Dist: numpy; extra == "viz"
Requires-Dist: matplotlib; extra == "viz"
Requires-Dist: ipython; extra == "viz"
Dynamic: author
Dynamic: classifier
Dynamic: description
Dynamic: description-content-type
Dynamic: provides-extra
Dynamic: requires-dist
Dynamic: requires-python
Dynamic: summary
